Workbook
Name Slicer_Category: #N/A
Name Slicer_Product: #N/A
Name Slicer_Region: #N/A

Sheet Raw Data
A1: Order ID | B1: Order Date | C1: Region | D1: Product | E1: Category | F1: Units Sold | G1: Unit Price | H1: Discount | I1: Sales | J1: Cost | K1: Profit | L1: Month | M1: Profit Margin
A2: ORD0001 | B2: 45760 | C2: South | D2: Tablet | E2: Electronics | F2: 4 | G2: 626.84 | H2: 0.1 | I2: 2256.62 | J2: 1633.07 | K2: 623.55 | L2: Apr | M2: 0.2763
A3: ORD0002 | B3: 45809 | C3: East | D3: Keyboard | E3: Accessories | F3: 7 | G3: 30.52 | H3: 0.1 | I3: 192.28 | J3: 139.26 | K3: 53.02 | L3: Jun | M3: 0.2757 | O3: sum of sales | P3: sum of profit | Q3: sum of unit | R3: Count of orderid
A4: ORD0003 | B4: 45849 | C4: West | D4: Webcam | E4: Accessories | F4: 5 | G4: 156.09 | H4: 0.1 | I4: 702.41 | J4: 443.19 | K4: 259.22 | L4: Jul | M4: 0.369 | O4: =SUM(I2:I751) -> 753637.49 | P4: =SUM(K2:K751) -> 221240.22 | Q4: =SUM(F2:F751) -> 3020 | R4: =COUNTA(A2:A751) -> 750
A5: ORD0004 | B5: 45706 | C5: East | D5: Headphones | E5: Accessories | F5: 1 | G5: 91.28 | H5: 0.05 | I5: 86.72 | J5: 59.29 | K5: 27.43 | L5: Feb | M5: 0.3163
A6: ORD0005 | B6: 45847 | C6: South | D6: Keyboard | E6: Accessories | F6: 7 | G6: 38.25 | H6: 0 | I6: 267.75 | J6: 178.84 | K6: 88.91 | L6: Jul | M6: 0.3321 | O6: =221240.22/753637.49% -> 29.356318
A7: ORD0006 | B7: 45788 | C7: North | D7: Tablet | E7: Electronics | F7: 6 | G7: 273.85 | H7: 0.05 | I7: 1560.95 | J7: 1127.29 | K7: 433.66 | L7: May | M7: 0.2778
A8: ORD0007 | B8: 45973 | C8: South | D8: Keyboard | E8: Accessories | F8: 7 | G8: 41.2 | H8: 0 | I8: 288.4 | J8: 232.95 | K8: 55.45 | L8: Nov | M8: 0.1923
A9: ORD0008 | B9: 45921 | C9: East | D9: Monitor | E9: Electronics | F9: 2 | G9: 234.43 | H9: 0 | I9: 468.86 | J9: 348.93 | K9: 119.93 | L9: Sep | M9: 0.2558
A10: ORD0009 | B10: 45711 | C10: South | D10: Keyboard | E10: Accessories | F10: 6 | G10: 62.15 | H10: 0 | I10: 372.9 | J10: 283.88 | K10: 89.02 | L10: Feb | M10: 0.2387
A11: ORD0010 | B11: 45859 | C11: South | D11: Mouse | E11: Accessories | F11: 6 | G11: 13.97 | H11: 0.1 | I11: 75.44 | J11: 51.9 | K11: 23.54 | L11: Jul | M11: 0.312
A12: ORD0011 | B12: 45909 | C12: North | D12: Mouse | E12: Accessories | F12: 6 | G12: 57.82 | H12: 0 | I12: 346.92 | J12: 248.71 | K12: 98.21 | L12: Sep | M12: 0.2831
A13: ORD0012 | B13: 45874 | C13: West | D13: Webcam | E13: Accessories | F13: 5 | G13: 80.53 | H13: 0 | I13: 402.65 | J13: 313.62 | K13: 89.03 | L13: Aug | M13: 0.2211
A14: ORD0013 | B14: 46002 | C14: East | D14: Mouse | E14: Accessories | F14: 4 | G14: 29.39 | H14: 0 | I14: 117.56 | J14: 72.85 | K14: 44.71 | L14: Dec | M14: 0.3803
A15: ORD0014 | B15: 45738 | C15: West | D15: Laptop | E15: Electronics | F15: 1 | G15: 679.17 | H15: 0 | I15: 679.17 | J15: 526.84 | K15: 152.33 | L15: Mar | M15: 0.2243
A16: ORD0015 | B16: 45698 | C16: West | D16: Keyboard | E16: Accessories | F16: 3 | G16: 98.27 | H16: 0 | I16: 294.81 | J16: 196.35 | K16: 98.46 | L16: Feb | M16: 0.334
A17: ORD0016 | B17: 45719 | C17: West | D17: Tablet | E17: Electronics | F17: 1 | G17: 472.95 | H17: 0 | I17: 472.95 | J17: 281.53 | K17: 191.42 | L17: Mar | M17: 0.4047
A18: ORD0017 | B18: 45884 | C18: North | D18: Headphones | E18: Accessories | F18: 3 | G18: 144.39 | H18: 0 | I18: 433.17 | J18: 309.59 | K18: 123.58 | L18: Aug | M18: 0.2853
... A751: ORD0750 | B751: 45940 | C751: East | D751: Mouse | E751: Accessories | F751: 5 | G751: 47.67 | H751: 0 | I751: 238.35 | J751: 141.78 | K751: 96.57 | L751: Oct | M751: 0.4052

Sheet Sheet1
A3: Row Labels | B3: Sum of Sales
A4: East | B4: 27380.58
A5: North | B5: 30686.35
A6: South | B6: 27298.84
A7: West | B7: 28768.12
A8: Grand Total | B8: 114133.89

Sheet Sheet2
A3: Row Labels | B3: Sum of Sales | C3: Sum of Profit
A4: Headphones | B4: 36167.72 | C4: 10237.58 | D4: =C4/B4 -> 0.28305848
A5: Webcam | B5: 34266.54 | C5: 10305.82 | D5: =C5/B5 -> 0.30075461
A6: Keyboard | B6: 28122.05 | C6: 8004.19 | D6: =C6/B6 -> 0.28462328
A7: Mouse | B7: 15577.58 | C7: 4779.42 | D7: =C7/B7 -> 0.30681402
A8: Grand Total | B8: 114133.89 | C8: 33327.01 | D8: =C8/B8 -> 0.29199925
D9: =C9/B9 -> #DIV/0!
D10: =C10/B10 -> #DIV/0!
D11: =C11/B11 -> #DIV/0!

Sheet Sheet3
A3: Row Labels | B3: Sum of Sales | C3: Sum of Profit
A4: Jan | B4: 8361.46 | C4: 2332.81
A5: Feb | B5: 10410.55 | C5: 3057.92
A6: Mar | B6: 10611.17 | C6: 3110.97
A7: Apr | B7: 12244.44 | C7: 3470.97
A8: May | B8: 11029.15 | C8: 3450.56
A9: Jun | B9: 5911.66 | C9: 1763.12
A10: Jul | B10: 10215.67 | C10: 3001.18
A11: Aug | B11: 8488.91 | C11: 2527.97
A12: Sep | B12: 9268.31 | C12: 2696.1
A13: Oct | B13: 8847.69 | C13: 2356
A14: Nov | B14: 7616.05 | C14: 2341.81
A15: Dec | B15: 11128.83 | C15: 3217.6
A16: Grand Total | B16: 114133.89 | C16: 33327.01

Sheet Dashboard
B2: SALES & BUSINESS PERFORMANCE DASHBOARD
B4: TOTAL SALES | D4: TOTAL PROFIT | F4: TOTAL ORDERS | H4: TOTAL UNITS | J4: PROFIT MARGIN
B5: =SUM('Raw Data'!I2:I751) -> 753637.49 | D5: =SUM('Raw Data'!K2:K751) -> 221240.22 | F5: =COUNTA('Raw Data'!A:A)-1 -> 750 | H5: =SUM('Raw Data'!F2:F751) -> 3020 | J5: =D5/B5 -> 0.29356318

Sheet Sheet4

Sheet Analysis
A1: Metric | B1: Value
A2: Total Sales | B2: =SUM('Raw Data'!I:I) -> 753637.49
A3: Total Profit | B3: =SUM('Raw Data'!K:K) -> 221240.22
A4: Total Orders | B4: =COUNTA('Raw Data'!A:A)-1 -> 750
A5: Total Units | B5: =SUM('Raw Data'!F:F) -> 3020
